Verilog/Async_FIFO.srcs/sources_1/new/fifo_mem.v
`timescale 1ns / 1ps
//////////////////////////////////////////////////////////////////////////////////
// Company: 
// Engineer: 
// 
// Create Date: 03/25/2026 05:13:47 PM
// Design Name: 
// Module Name: fifo_mem
// Project Name: 
// Target Devices: 
// Tool Versions: 
// Description: 
// 
// Dependencies: 
// 
// Revision:
// Revision 0.01 - File Created
// Additional Comments:
// 
//////////////////////////////////////////////////////////////////////////////////


module fifo_mem #(
    parameter DEPTH = 16,
    parameter DATA_WIDTH = 8,
    parameter PTR_WIDTH = 4
)(
    input wr_clk,
    input wr_en,
    input rd_clk,
    input rd_en,
    input [PTR_WIDTH:0] b_wptr,
    input [PTR_WIDTH:0] b_rptr,
    input [DATA_WIDTH-1:0] data_in,
    input full,
    input empty,
    output reg [DATA_WIDTH-1:0] data_out
    );

    reg [DATA_WIDTH-1:0] fifo [0:DEPTH-1];

    always @(posedge wr_clk) begin
        if (wr_en && !full) begin
            fifo[b_wptr[PTR_WIDTH-1:0]] <= data_in;
        end
    end

    always @(posedge rd_clk) begin
        if (rd_en && !empty) begin
            data_out <= fifo[b_rptr[PTR_WIDTH-1:0]];
        end
    end

endmodule

Verilog/Async_FIFO.srcs/sources_1/new/rdptr_empty.v
`timescale 1ns / 1ps
//////////////////////////////////////////////////////////////////////////////////
// Company: 
// Engineer: 
// 
// Create Date: 03/25/2026 05:16:47 PM
// Design Name: 
// Module Name: rdptr_empty
// Project Name: 
// Target Devices: 
// Tool Versions: 
// Description: 
// 
// Dependencies: 
// 
// Revision:
// Revision 0.01 - File Created
// Additional Comments:
// 
//////////////////////////////////////////////////////////////////////////////////


module rdptr_empty #(parameter PTR_WIDTH = 4)(
    input rd_clk,
    input rd_rst_n,
    input rd_en,
    input [PTR_WIDTH:0] g_wptr_sync,
    output reg empty,
    output reg [PTR_WIDTH:0] g_rptr,
    output reg [PTR_WIDTH:0] b_rptr
    );

    wire [PTR_WIDTH:0] b_rptr_next;
    wire [PTR_WIDTH:0] g_rptr_next;
    wire rd_empty;

    assign b_rptr_next = b_rptr + (rd_en && !empty);
    assign g_rptr_next = (b_rptr_next >> 1) ^ b_rptr_next;
    assign rd_empty = (g_wptr_sync == g_rptr_next);

    always @(posedge rd_clk or negedge rd_rst_n) begin
        if (!rd_rst_n) begin
            b_rptr <= 0;
            g_rptr <= 0;
        end else begin
            b_rptr <= b_rptr_next;
            g_rptr <= g_rptr_next;
        end
    end

    always @(posedge rd_clk or negedge rd_rst_n) begin
        if (!rd_rst_n) begin
            empty <= 1;
        end else begin
            empty <= rd_empty;
        end
    end

endmodule

Verilog/Async_FIFO.srcs/sources_1/new/wrptr_full.v
`timescale 1ns / 1ps
//////////////////////////////////////////////////////////////////////////////////
// Company: 
// Engineer: 
// 
// Create Date: 03/25/2026 05:16:33 PM
// Design Name: 
// Module Name: wrptr_full
// Project Name: 
// Target Devices: 
// Tool Versions: 
// Description: 
// 
// Dependencies: 
// 
// Revision:
// Revision 0.01 - File Created
// Additional Comments:
// 
//////////////////////////////////////////////////////////////////////////////////


module wrptr_full #(parameter PTR_WIDTH = 4)(
    input wr_clk,
    input wr_rst_n,
    input wr_en,
    input [PTR_WIDTH:0] g_rptr_sync,
    output reg full,
    output reg [PTR_WIDTH:0] g_wptr,
    output reg [PTR_WIDTH:0] b_wptr
    );

    wire [PTR_WIDTH:0] b_wptr_next;
    wire [PTR_WIDTH:0] g_wptr_next;
    wire wr_full;

    assign b_wptr_next = b_wptr + (wr_en && !full);
    assign g_wptr_next = (b_wptr_next >> 1) ^ b_wptr_next;
    assign wr_full = (
        g_wptr_next == {~g_rptr_sync[PTR_WIDTH:PTR_WIDTH-1], g_rptr_sync[PTR_WIDTH-2:0]}
    );

    always @(posedge wr_clk or negedge wr_rst_n) begin
        if (!wr_rst_n) begin
            b_wptr <= 0;
            g_wptr <= 0;
        end else begin
            b_wptr <= b_wptr_next;
            g_wptr <= g_wptr_next;
        end
    end

    always @(posedge wr_clk or negedge wr_rst_n) begin
        if (!wr_rst_n) begin
            full <= 0;
        end else begin
            full <= wr_full;
        end
    end
endmodule

Verilog/Async_FIFO.srcs/sources_1/new/sync.v
`timescale 1ns / 1ps
//////////////////////////////////////////////////////////////////////////////////
// Company: 
// Engineer: 
// 
// Create Date: 03/25/2026 05:13:02 PM
// Design Name: 
// Module Name: sync
// Project Name: 
// Target Devices: 
// Tool Versions: 
// Description: 
// 
// Dependencies: 
// 
// Revision:
// Revision 0.01 - File Created
// Additional Comments:
// 
//////////////////////////////////////////////////////////////////////////////////


module sync #(parameter SIZE = 4)(
    output reg [SIZE-1:0] data_out,
    input [SIZE-1:0] data_in,
    input clk,
    input rst_n
    );

    (* ASYNC_REG = "TRUE" *) reg [SIZE-1:0] ff_1;

    always @(posedge clk or negedge rst_n) begin
        if (!rst_n) begin
            ff_1 <= 0;
            data_out <= 0;
        end else begin
            ff_1 <= data_in;
            data_out <= ff_1;
        end
    end

endmodule

Verilog/Async_FIFO.srcs/sources_1/new/TOP.v
`timescale 1ns / 1ps
//////////////////////////////////////////////////////////////////////////////////
// Company: 
// Engineer: 
// 
// Create Date: 03/25/2026 05:17:07 PM
// Design Name: 
// Module Name: TOP
// Project Name: 
// Target Devices: 
// Tool Versions: 
// Description: 
// 
// Dependencies: 
// 
// Revision:
// Revision 0.01 - File Created
// Additional Comments:
// 
//////////////////////////////////////////////////////////////////////////////////


module TOP #(
    parameter DEPTH = 16,
    parameter DATA_WIDTH = 8
) (
    input wr_clk,
    input wr_rst_n,
    input rd_clk,
    input rd_rst_n,
    input wr_en,
    input rd_en,
    input [DATA_WIDTH-1:0] data_in,
    output [DATA_WIDTH-1:0] data_out,
    output full,
    output empty
    );

    localparam PTR_WIDTH = $clog2(DEPTH);

    wire [PTR_WIDTH:0] g_wptr_sync;
    wire [PTR_WIDTH:0] g_rptr_sync;
    wire [PTR_WIDTH:0] b_wptr;
    wire [PTR_WIDTH:0] b_rptr;
    wire [PTR_WIDTH:0] g_wptr;
    wire [PTR_WIDTH:0] g_rptr;

    sync #(PTR_WIDTH + 1) sync_wptr_inst (
        .data_out(g_wptr_sync),
        .data_in(g_wptr),
        .clk(rd_clk),
        .rst_n(rd_rst_n)
    );

    sync #(PTR_WIDTH + 1) sync_rptr_inst (
        .data_out(g_rptr_sync),
        .data_in(g_rptr),
        .clk(wr_clk),
        .rst_n(wr_rst_n)
    );

    wrptr_full #(PTR_WIDTH) wptr_full_inst (
        .wr_clk(wr_clk),
        .wr_rst_n(wr_rst_n),
        .wr_en(wr_en),
        .g_rptr_sync(g_rptr_sync),
        .full(full),
        .g_wptr(g_wptr),
        .b_wptr(b_wptr)
    );

    rdptr_empty #(PTR_WIDTH) rptr_empty_inst (
        .rd_clk(rd_clk),
        .rd_rst_n(rd_rst_n),
        .rd_en(rd_en),
        .g_wptr_sync(g_wptr_sync),
        .empty(empty),
        .g_rptr(g_rptr),
        .b_rptr(b_rptr)
    );

    fifo_mem #(
        .DEPTH(DEPTH),
        .DATA_WIDTH(DATA_WIDTH),
        .PTR_WIDTH(PTR_WIDTH)
    ) fifo_mem_inst (
        .wr_clk(wr_clk),
        .wr_en(wr_en),
        .rd_clk(rd_clk),
        .rd_en(rd_en),
        .b_wptr(b_wptr),
        .b_rptr(b_rptr),
        .data_in(data_in),
        .full(full),
        .empty(empty),
        .data_out(data_out)
    );

endmodule

Verilog/Async_FIFO.srcs/sim_1/new/Async_FIFO_tb.v
`timescale 1ns / 1ps
//////////////////////////////////////////////////////////////////////////////////
// Company: 
// Engineer: 
// 
// Create Date: 03/25/2026 08:26:00 PM
// Design Name: 
// Module Name: Async_FIFO_tb
// Project Name: 
// Target Devices: 
// Tool Versions: 
// Description: 
// 
// Dependencies: 
// 
// Revision:
// Revision 0.01 - File Created
// Additional Comments:
// 
//////////////////////////////////////////////////////////////////////////////////


module Async_FIFO_tb;
    parameter DEPTH = 16;
    parameter DATA_WIDTH = 8;
    parameter PRELOAD_COUNT = 8;
    parameter STRESS_COUNT = 16;
    parameter TOTAL_TRANSFERS = PRELOAD_COUNT + STRESS_COUNT;

    reg wr_clk;
    reg wr_rst_n;
    reg rd_clk;
    reg rd_rst_n;
    reg wr_en;
    reg rd_en;
    reg [DATA_WIDTH-1:0] data_in;

    wire [DATA_WIDTH-1:0] data_out;
    wire full;
    wire empty;

    reg [DATA_WIDTH-1:0] exp_mem [0:TOTAL_TRANSFERS-1];
    reg [DATA_WIDTH-1:0] exp_data;
    integer wr_count;
    integer rd_count;
    integer i;
    integer wr_idx;
    integer rd_idx;
    integer pass_count;

    TOP #(
        .DEPTH(DEPTH),
        .DATA_WIDTH(DATA_WIDTH)
    ) dut (
        .wr_clk(wr_clk),
        .wr_rst_n(wr_rst_n),
        .rd_clk(rd_clk),
        .rd_rst_n(rd_rst_n),
        .wr_en(wr_en),
        .rd_en(rd_en),
        .data_in(data_in),
        .data_out(data_out),
        .full(full),
        .empty(empty)
    );

    always #10 wr_clk = ~wr_clk;
    always #35 rd_clk = ~rd_clk;

    task write_word;
        input [DATA_WIDTH-1:0] value;
        begin
            while (full) begin
                @(posedge wr_clk);
            end

            @(negedge wr_clk);
            wr_en = 1'b1;
            data_in = value;

            @(posedge wr_clk);
            exp_mem[wr_count] = value;
            wr_count = wr_count + 1;

            @(negedge wr_clk);
            wr_en = 1'b0;
            data_in = {DATA_WIDTH{1'b0}};
        end
    endtask

    task read_and_check;
        begin
            while (empty) begin
                @(posedge rd_clk);
            end

            exp_data = exp_mem[rd_count];

            @(negedge rd_clk);
            rd_en = 1'b1;

            @(posedge rd_clk);
            #1;
            if (data_out !== exp_data) begin
                $error(
                    "Time=%0t Read mismatch at index %0d: expected=%h actual=%h",
                    $time,
                    rd_count,
                    exp_data,
                    data_out
                );
            end else begin
                pass_count = pass_count + 1;
                $display(
                    "Time=%0t Read pass at index %0d: data=%h",
                    $time,
                    rd_count,
                    data_out
                );
            end

            rd_count = rd_count + 1;

            @(negedge rd_clk);
            rd_en = 1'b0;
        end
    endtask

    initial begin
        wr_clk = 1'b0;
        wr_rst_n = 1'b0;
        rd_clk = 1'b0;
        rd_rst_n = 1'b0;
        wr_en = 1'b0;
        rd_en = 1'b0;
        data_in = {DATA_WIDTH{1'b0}};
        exp_data = {DATA_WIDTH{1'b0}};
        wr_count = 0;
        rd_count = 0;
        pass_count = 0;
    end

    initial begin
        repeat (4) @(posedge wr_clk);
        wr_rst_n = 1'b1;
    end

    initial begin
        repeat (4) @(posedge rd_clk);
        rd_rst_n = 1'b1;
    end

    initial begin
        wait (wr_rst_n && rd_rst_n);

        repeat (2) @(posedge wr_clk);

        for (i = 0; i < PRELOAD_COUNT; i = i + 1) begin
            write_word(i[DATA_WIDTH-1:0]);
        end

        repeat (3) @(posedge rd_clk);

        for (i = 0; i < PRELOAD_COUNT; i = i + 1) begin
            read_and_check;
        end

        fork
            begin
                for (wr_idx = 0; wr_idx < STRESS_COUNT; wr_idx = wr_idx + 1) begin
                    write_word($random);
                end
            end
            begin
                for (rd_idx = 0; rd_idx < STRESS_COUNT; rd_idx = rd_idx + 1) begin
                    read_and_check;
                end
            end
        join

        repeat (4) @(posedge rd_clk);

        if (!empty) begin
            $error("FIFO should be empty at end of test");
        end

        $display("Simulation completed with %0d successful read checks.", pass_count);
        $finish;
    end

    initial begin
        #5000;
        $fatal(1, "Timeout waiting for testbench completion");
    end

    initial begin
        $dumpfile("dump.vcd");
        $dumpvars(0, Async_FIFO_tb);
    end

endmodule

Verilog/Async_FIFO.sim/sim_1/behav/xsim/dump.vcd
$date
   Wed Mar 25 20:42:22 2026
$end
$version
  2022.2
$end
$timescale
  1ps
$end
$scope module Async_FIFO_tb $end
$var reg 1 ! wr_clk $end
$var reg 1 " wr_rst_n $end
$var reg 1 # rd_clk $end
$var reg 1 $ rd_rst_n $end
$var reg 1 % wr_en $end
$var reg 1 & rd_en $end
$var reg 8 ' data_in [7:0] $end
$var wire 8 ( data_out [7:0] $end
$var wire 1 ) full $end
$var wire 1 * empty $end
$var reg 8 + exp_data [7:0] $end
$var integer 32 , wr_count [31:0] $end
$var integer 32 - rd_count [31:0] $end
$var integer 32 . i [31:0] $end
$var integer 32 / wr_idx [31:0] $end
$var integer 32 0 rd_idx [31:0] $end
$var integer 32 1 pass_count [31:0] $end
$scope module dut $end
$var wire 1 2 wr_clk $end
$var wire 1 3 wr_rst_n $end
$var wire 1 4 rd_clk $end
$var wire 1 5 rd_rst_n $end
$var wire 1 6 wr_en $end
$var wire 1 7 rd_en $end
$var wire 8 8 data_in [7:0] $end
$var wire 8 ( data_out [7:0] $end
$var wire 1 ) full $end
$var wire 1 * empty $end
$var wire 5 9 g_wptr_sync [4:0] $end
$var wire 5 : g_rptr_sync [4:0] $end
$var wire 5 ; b_wptr [4:0] $end
$var wire 5 < b_rptr [4:0] $end
$var wire 5 = g_wptr [4:0] $end
$var wire 5 > g_rptr [4:0] $end
$scope module sync_wptr_inst $end
$var reg 5 ? data_out [4:0] $end
$var wire 5 = data_in [4:0] $end
$var wire 1 4 clk $end
$var wire 1 5 rst_n $end
$var reg 5 @ ff_1 [4:0] $end
$upscope $end
$scope module sync_rptr_inst $end
$var reg 5 A data_out [4:0] $end
$var wire 5 > data_in [4:0] $end
$var wire 1 2 clk $end
$var wire 1 3 rst_n $end
$var reg 5 B ff_1 [4:0] $end
$upscope $end
$scope module wptr_full_inst $end
$var wire 1 2 wr_clk $end
$var wire 1 3 wr_rst_n $end
$var wire 1 6 wr_en $end
$var wire 5 : g_rptr_sync [4:0] $end
$var reg 1 C full $end
$var reg 5 D g_wptr [4:0] $end
$var reg 5 E b_wptr [4:0] $end
$var wire 5 F b_wptr_next [4:0] $end
$var wire 5 G g_wptr_next [4:0] $end
$var wire 1 H wr_full $end
$upscope $end
$scope module rptr_empty_inst $end
$var wire 1 4 rd_clk $end
$var wire 1 5 rd_rst_n $end
$var wire 1 7 rd_en $end
$var wire 5 9 g_wptr_sync [4:0] $end
$var reg 1 I empty $end
$var reg 5 J g_rptr [4:0] $end
$var reg 5 K b_rptr [4:0] $end
$var wire 5 L b_rptr_next [4:0] $end
$var wire 5 M g_rptr_next [4:0] $end
$var wire 1 N rd_empty $end
$upscope $end
$scope module fifo_mem_inst $end
$var wire 1 2 wr_clk $end
$var wire 1 6 wr_en $end
$var wire 1 4 rd_clk $end
$var wire 1 7 rd_en $end
$var wire 5 ; b_wptr [4:0] $end
$var wire 5 < b_rptr [4:0] $end
$var wire 8 8 data_in [7:0] $end
$var wire 1 ) full $end
$var wire 1 * empty $end
$var reg 8 O data_out [7:0] $end
$upscope $end
$upscope $end
$scope task write_word $end
$var reg 8 P value [7:0] $end
$upscope $end
$scope task read_and_check $end
$upscope $end
$upscope $end
$enddefinitions $end
#0
$dumpvars
0!
0"
0#
0$
0%
0&
b0 '
bx (
0)
1*
b0 +
b0 ,
b0 -
bx .
bx /
bx 0
b0 1
02
03
04
05
06
07
b0 8
b0 9
b0 :
b0 ;
b0 <
b0 =
b0 >
b0 ?
b0 @
b0 A
b0 B
0C
b0 D
b0 E
b0 F
b0 G
0H
1I
b0 J
b0 K
b0 L
b0 M
1N
bx O
bx P
$end
#10000
1!
12
#20000
0!
02
#30000
1!
12
#35000
1#
14
#40000
0!
02
#50000
1!
12
#60000
0!
02
#70000
1!
1"
0#
12
13
04
#80000
0!
02
#90000
1!
12
#100000
0!
02
#105000
1#
14
#110000
1!
12
#120000
0!
02
#130000
1!
12
#140000
0!
0#
02
04
#150000
1!
12
#160000
0!
02
#170000
1!
12
#175000
1#
14
#180000
0!
02
#190000
1!
12
#200000
0!
02
#210000
1!
0#
12
04
#220000
0!
02
#230000
1!
12
#240000
0!
02
#245000
1#
1$
14
15
#250000
1!
12
#260000
0!
02
#270000
1!
b0 .
12
b0 P
#280000
0!
0#
1%
b0 '
02
04
16
b1 F
b1 G
#290000
1!
b1 ,
12
b1 ;
b1 =
b1 D
b1 E
b10 F
b11 G
#300000
0!
0%
b0 '
b1 .
02
06
b1 F
b1 G
b1 P
#310000
1!
12
#315000
1#
14
b1 @
#320000
0!
1%
b1 '
02
16
b1 8
b10 F
b11 G
#330000
1!
b10 ,
12
b10 ;
b11 =
b11 D
b10 E
b11 F
b10 G
#340000
0!
0%
b0 '
b10 .
02
06
b0 8
b10 F
b11 G
b10 P
#350000
1!
0#
12
04
#360000
0!
1%
b10 '
02
16
b10 8
b11 F
b10 G
#370000
1!
b11 ,
12
b11 ;
b10 =
b10 D
b11 E
b100 F
b110 G
#380000
0!
0%
b0 '
b11 .
02
06
b0 8
b11 F
b10 G
b11 P
#385000
1#
14
b1 9
b1 ?
b10 @
0N
#390000
1!
12
#400000
0!
1%
b11 '
02
16
b11 8
b100 F
b110 G
#410000
1!
b100 ,
12
b100 ;
b110 =
b110 D
b100 E
b101 F
b111 G
#420000
0!
0#
0%
b0 '
b100 .
02
04
06
b0 8
b100 F
b110 G
b100 P
#430000
1!
12
#440000
0!
1%
b100 '
02
16
b100 8
b101 F
b111 G
#450000
1!
b101 ,
12
b101 ;
b111 =
b111 D
b101 E
b110 F
b101 G
#455000
1#
0*
14
b10 9
b10 ?
b111 @
0I
b0 L
#460000
0!
0%
b0 '
b101 .
02
06
b0 8
b101 F
b111 G
b101 P
#470000
1!
12
#480000
0!
1%
b101 '
02
16
b101 8
b110 F
b101 G
#490000
1!
0#
b110 ,
12
04
b110 ;
b101 =
b101 D
b110 E
b111 F
b100 G
#500000
0!
0%
b0 '
b110 .
02
06
b0 8
b110 F
b101 G
b110 P
#510000
1!
12
#520000
0!
1%
b110 '
02
16
b110 8
b111 F
b100 G
#525000
1#
14
b111 9
b111 ?
b101 @
#530000
1!
b111 ,
12
b111 ;
b100 =
b100 D
b111 E
b1000 F
b1100 G
#540000
0!
0%
b0 '
b111 .
02
06
b0 8
b111 F
b100 G
b111 P
#550000
1!
12
#560000
0!
0#
1%
b111 '
02
04
16
b111 8
b1000 F
b1100 G
#570000
1!
b1000 ,
12
b1000 ;
b1100 =
b1100 D
b1000 E
b1001 F
b1101 G
#580000
0!
0%
b0 '
b1000 .
02
06
b0 8
b1000 F
b1100 G
#590000
1!
12
#595000
1#
14
b101 9
b101 ?
b1100 @
#600000
0!
02
#610000
1!
12
#620000
0!
02
#630000
1!
0#
12
04
#640000
0!
02
#650000
1!
12
#660000
0!
02
#665000
1#
14
b1100 9
b1100 ?
#670000
1!
12
#680000
0!
02
#690000
1!
12
#700000
0!
0#
02
04
#710000
1!
12
#720000
0!
02
#730000
1!
12
#735000
1#
b0 .
14
#740000
0!
02
#750000
1!
12
#760000
0!
02
#770000
1!
0#
1&
12
04
17
b1 L
b1 M
#780000
0!
02
#790000
1!
12
#800000
0!
02
#805000
1#
b0 (
14
b1 <
b1 >
b1 J
b1 K
b10 L
b11 M
b0 O
#806000
b1 -
b1 1
#810000
1!
12
b1 B
#820000
0!
02
#830000
1!
12
b1 :
b1 A
#840000
0!
0#
0&
b1 +
b1 .
02
04
07
b1 L
b1 M
#850000
1!
12
#860000
0!
02
#870000
1!
12
#875000
1#
14
#880000
0!
02
#890000
1!
12
#900000
0!
02
#910000
1!
0#
1&
12
04
17
b10 L
b11 M
#920000
0!
02
#930000
1!
12
#940000
0!
02
#945000
1#
b1 (
14
b10 <
b11 >
b11 J
b10 K
b11 L
b10 M
b1 O
#946000
b10 -
b10 1
#950000
1!
12
b11 B
#960000
0!
02
#970000
1!
12
b11 :
b11 A
#980000
0!
0#
0&
b10 +
b10 .
02
04
07
b10 L
b11 M
