Verilog/Async_FIFO.srcs/sources_1/new/fifo_mem.v
`timescale 1ns / 1ps
//////////////////////////////////////////////////////////////////////////////////
// Company: 
// Engineer: 
// 
// Create Date: 03/25/2026 05:13:47 PM
// Design Name: 
// Module Name: fifo_mem
// Project Name: 
// Target Devices: 
// Tool Versions: 
// Description:
// Storage array for the asynchronous FIFO. The write side updates memory on
// `wr_clk`, and the read side exposes the selected entry from the read pointer.
// 
// Dependencies: 
// 
// Revision:
// Revision 0.01 - File Created
// Additional Comments:
// Only the lower pointer bits address the RAM. The extra MSB in each pointer
// is used by the full/empty logic to track wrap-around.
// 
//////////////////////////////////////////////////////////////////////////////////


module fifo_mem #(
    parameter DATA_WIDTH = 8,
    parameter PTR_WIDTH = 5,
    parameter DEPTH = 16 
)(
    input wr_clk,
    input wr_en,
    input rd_clk,
    input rd_en,
    input [PTR_WIDTH-1:0] b_wptr,
    input [PTR_WIDTH-1:0] b_rptr,
    input [DATA_WIDTH-1:0] data_in,
    input full,
    input empty,
    output [DATA_WIDTH-1:0] data_out
    );
    
    localparam ADD_SIZE = PTR_WIDTH - 1;

    // FIFO storage depth is indexed by the binary address bits only.
    reg [DATA_WIDTH-1:0] fifo [0:DEPTH-1];
    
    always @(posedge wr_clk) begin
        if (wr_en && !full) begin
            // Write new data into the slot selected by the current write pointer.
            fifo[b_wptr[ADD_SIZE-1:0]] <= data_in;
        end
    end

//    always @(posedge rd_clk) begin
//        if (rd_en && !empty) begin
//            data_out <= fifo[b_rptr[PTR_WIDTH-1:0]];
//        end
//    end
    // The current design uses a combinational read path from the selected slot.
    assign data_out = fifo[b_rptr[ADD_SIZE-1:0]];

endmodule

Verilog/Async_FIFO.srcs/sources_1/new/rdptr_empty.v
`timescale 1ns / 1ps
//////////////////////////////////////////////////////////////////////////////////
// Company: 
// Engineer: 
// 
// Create Date: 03/25/2026 05:16:47 PM
// Design Name: 
// Module Name: rdptr_empty
// Project Name: 
// Target Devices: 
// Tool Versions: 
// Description:
// Read-pointer control for the asynchronous FIFO. This module advances the
// read pointer and generates the `empty` flag in the read clock domain.
// 
// Dependencies: 
// 
// Revision:
// Revision 0.01 - File Created
// Additional Comments:
// The module keeps both binary and Gray-coded read pointers. Empty is detected
// by comparing the next Gray read pointer against the synchronized write pointer.
// 
//////////////////////////////////////////////////////////////////////////////////


module rdptr_empty #(parameter PTR_WIDTH = 5)(
    input rd_clk,
    input rd_rst_n,
    input rd_en,
    input [PTR_WIDTH-1:0] g_wptr_sync,
    output reg empty,
    output reg [PTR_WIDTH-1:0] g_rptr,
    output reg [PTR_WIDTH-1:0] b_rptr
    );

    localparam ADD_SIZE = PTR_WIDTH - 1;

    wire [PTR_WIDTH-1:0] b_rptr_next;
    wire [PTR_WIDTH-1:0] g_rptr_next;
    wire rd_empty;

    // Advance only when a read is requested and the FIFO is not empty.
    assign b_rptr_next = b_rptr + (rd_en && !empty);
    // Convert the next binary pointer into Gray code for CDC-safe comparison.
    assign g_rptr_next = (b_rptr_next >> 1) ^ b_rptr_next;
    // FIFO is empty when the next read pointer catches the synchronized write pointer.
    assign rd_empty = (g_wptr_sync == g_rptr_next);

    always @(posedge rd_clk or negedge rd_rst_n) begin
        if (!rd_rst_n) begin
            b_rptr <= 0;
            g_rptr <= 0;
        end else begin
            // Update both pointer forms together each read clock.
            b_rptr <= b_rptr_next;
            g_rptr <= g_rptr_next;
        end
    end

    always @(posedge rd_clk or negedge rd_rst_n) begin
        if (!rd_rst_n) begin
            empty <= 1;
        end else begin
            // Register the empty flag to keep it aligned with read-domain timing.
            empty <= rd_empty;
        end
    end

endmodule

Verilog/Async_FIFO.srcs/sources_1/new/wrptr_full.v
`timescale 1ns / 1ps
//////////////////////////////////////////////////////////////////////////////////
// Company: 
// Engineer: 
// 
// Create Date: 03/25/2026 05:16:33 PM
// Design Name: 
// Module Name: wrptr_full
// Project Name: 
// Target Devices: 
// Tool Versions: 
// Description:
// Write-pointer control for the asynchronous FIFO. This module advances the
// write pointer and generates the `full` flag in the write clock domain.
// 
// Dependencies: 
// 
// Revision:
// Revision 0.01 - File Created
// Additional Comments:
// The module keeps both binary and Gray-coded write pointers. Gray code is
// compared against the synchronized read pointer to detect a full condition.
// 
//////////////////////////////////////////////////////////////////////////////////


module wrptr_full #(
    parameter PTR_WIDTH = 5
    )(
    input wr_clk,
    input wr_rst_n,
    input wr_en,
    input [PTR_WIDTH-1:0] g_rptr_sync,
    output reg full,
    output reg [PTR_WIDTH-1:0] g_wptr,
    output reg [PTR_WIDTH-1:0] b_wptr
    );
    
    localparam ADD_SIZE = PTR_WIDTH - 1;

    wire [PTR_WIDTH-1:0] b_wptr_next;
    wire [PTR_WIDTH-1:0] g_wptr_next;
    wire wr_full;

    // Advance only when a write is requested and the FIFO is not full.
    assign b_wptr_next = b_wptr + (wr_en && !full);
    // Convert the next binary pointer into Gray code for CDC-safe comparison.
    assign g_wptr_next = (b_wptr_next >> 1) ^ b_wptr_next;
    // FIFO becomes full when the next write pointer reaches the read pointer
    // with the wrap bits inverted.
    assign wr_full = (
        g_wptr_next == {~g_rptr_sync[ADD_SIZE:ADD_SIZE-1], g_rptr_sync[ADD_SIZE-2:0]}
    );

    always @(posedge wr_clk or negedge wr_rst_n) begin
        if (!wr_rst_n) begin
            b_wptr <= 0;
            g_wptr <= 0;
        end else begin
            // Update both pointer forms together each write clock.
            b_wptr <= b_wptr_next;
            g_wptr <= g_wptr_next;
        end
    end

    always @(posedge wr_clk or negedge wr_rst_n) begin
        if (!wr_rst_n) begin
            full <= 1'b0;
        end else begin
            // Register the full flag to keep it aligned with write-domain timing.
            full <= wr_full;
        end
    end
        
endmodule

Verilog/Async_FIFO.srcs/sources_1/new/sync.v
`timescale 1ns / 1ps
//////////////////////////////////////////////////////////////////////////////////
// Company: 
// Engineer: 
// 
// Create Date: 03/25/2026 05:13:02 PM
// Design Name: 
// Module Name: sync
// Project Name: 
// Target Devices: 
// Tool Versions: 
// Description:
// Two-flop synchronizer used to transfer a Gray-coded pointer into a new
// clock domain inside the asynchronous FIFO.
// 
// Dependencies: 
// 
// Revision:
// Revision 0.01 - File Created
// Additional Comments:
// This module is intended for Gray-coded CDC paths. Gray code changes only
// one bit at a time, which makes multi-bit pointer synchronization safer.
// 
//////////////////////////////////////////////////////////////////////////////////


module sync #(parameter SIZE = 5)(
    output reg [SIZE-1:0] data_out,
    input [SIZE-1:0] data_in,
    input clk,
    input rst_n
    );

    reg [SIZE-1:0] ff_1;

    always @(posedge clk or negedge rst_n) begin
        if (!rst_n) begin
            // Clear both synchronizer stages when the local reset is asserted.
            {data_out, ff_1} <= 0; 
        end else begin
            // Stage 1 captures the incoming bus; stage 2 provides a settled
            // version to logic in this clock domain.
            {data_out, ff_1} <= {ff_1, data_in}; 
        end
    end

endmodule

Verilog/Async_FIFO.srcs/sources_1/new/TOP.v
`timescale 1ns / 1ps
//////////////////////////////////////////////////////////////////////////////////
// Company: 
// Engineer: 
// 
// Create Date: 03/25/2026 05:17:07 PM
// Design Name: 
// Module Name: TOP
// Project Name: 
// Target Devices: 
// Tool Versions: 
// Description:
// Top-level asynchronous FIFO wrapper that connects pointer synchronization,
// status generation, and the storage array across separate read/write clocks.
// 
// Dependencies: 
// 
// Revision:
// Revision 0.01 - File Created
// Additional Comments:
// Gray-coded pointers are synchronized into the opposite clock domain before
// they are used for full or empty detection.
// 
//////////////////////////////////////////////////////////////////////////////////


module TOP #(
    parameter DEPTH = 16,
    parameter DATA_WIDTH = 8
) (
    input wr_clk,
    input wr_rst_n,
    input rd_clk,
    input rd_rst_n,
    input wr_en,
    input rd_en,
    input [DATA_WIDTH-1:0] data_in,
    output [DATA_WIDTH-1:0] data_out,
    output full,
    output empty
    );

    // One extra pointer bit is used to distinguish wrap-around.
    localparam PTR_WIDTH = $clog2(DEPTH) + 1;

    wire [PTR_WIDTH-1:0] g_wptr_sync;
    wire [PTR_WIDTH-1:0] g_rptr_sync;
    wire [PTR_WIDTH-1:0] b_wptr;
    wire [PTR_WIDTH-1:0] b_rptr;
    wire [PTR_WIDTH-1:0] g_wptr;
    wire [PTR_WIDTH-1:0] g_rptr;

    // Synchronize the write pointer into the read clock domain.
    sync #(PTR_WIDTH) sync_wptr_inst (
        .data_out(g_wptr_sync),
        .data_in(g_wptr),
        .clk(rd_clk),
        .rst_n(rd_rst_n)
    );

    // Synchronize the read pointer into the write clock domain.
    sync #(PTR_WIDTH) sync_rptr_inst (
        .data_out(g_rptr_sync),
        .data_in(g_rptr),
        .clk(wr_clk),
        .rst_n(wr_rst_n)
    );

    // Generate the write-side pointer and full status.
    wrptr_full #(PTR_WIDTH) wptr_full_inst (
        .wr_clk(wr_clk),
        .wr_rst_n(wr_rst_n),
        .wr_en(wr_en),
        .g_rptr_sync(g_rptr_sync),
        .full(full),
        .g_wptr(g_wptr),
        .b_wptr(b_wptr)
    );

    // Generate the read-side pointer and empty status.
    rdptr_empty #(PTR_WIDTH) rptr_empty_inst (
        .rd_clk(rd_clk),
        .rd_rst_n(rd_rst_n),
        .rd_en(rd_en),
        .g_wptr_sync(g_wptr_sync),
        .empty(empty),
        .g_rptr(g_rptr),
        .b_rptr(b_rptr)
    );

    // Memory is addressed with the binary pointers from each side.
    fifo_mem #(
        .DEPTH(DEPTH),
        .DATA_WIDTH(DATA_WIDTH),
        .PTR_WIDTH(PTR_WIDTH)
    ) fifo_mem_inst (
        .wr_clk(wr_clk),
        .wr_en(wr_en),
        .rd_clk(rd_clk),
        .rd_en(rd_en),
        .b_wptr(b_wptr),
        .b_rptr(b_rptr),
        .data_in(data_in),
        .full(full),
        .empty(empty),
        .data_out(data_out)
    );

endmodule

Verilog/Async_FIFO.srcs/sim_1/new/Async_FIFO_tb.v
`timescale 1ns / 1ps
//////////////////////////////////////////////////////////////////////////////////
// Company:
// Engineer:
//
// Create Date: 03/25/2026 08:26:00 PM
// Design Name:
// Module Name: Async_FIFO_tb
// Project Name:
// Target Devices:
// Tool Versions:
// Description:
// Basic behavioral testbench for the asynchronous FIFO. It applies reset,
// performs write/read traffic, and exercises full and empty corner cases.
//
// Dependencies:
//
// Revision:
// Revision 0.01 - File Created
// Additional Comments:
// The two clocks run at different rates to mimic asynchronous operation.
//
//////////////////////////////////////////////////////////////////////////////////


module Async_FIFO_tb;

    parameter DSIZE = 8;
    parameter DEPTH = 16;

    reg [DSIZE-1:0] wr_data;
    reg w_inc;
    reg r_inc;
    reg wr_clk;
    reg rd_clk;
    reg wr_rst_n;
    reg rd_rst_n;

    wire [DSIZE-1:0] rd_data;
    wire wr_full;
    wire rd_empty;

    integer i;
    integer seed;

    TOP #(
        .DEPTH(DEPTH),
        .DATA_WIDTH(DSIZE)
    ) fifo (
        .wr_clk(wr_clk),
        .wr_rst_n(wr_rst_n),
        .rd_clk(rd_clk),
        .rd_rst_n(rd_rst_n),
        .wr_en(w_inc),
        .rd_en(r_inc),
        .data_in(wr_data),
        .data_out(rd_data),
        .full(wr_full),
        .empty(rd_empty)
    );

    // Write clock is faster than read clock in this testbench.
    always #5  wr_clk = ~wr_clk;
    always #10 rd_clk = ~rd_clk;

    always @(posedge wr_clk) begin
        if (w_inc && !wr_full) begin
            $display("Time=%0t WRITE data=%h full=%b empty=%b", $time, wr_data, wr_full, rd_empty);
        end else if (w_inc && wr_full) begin
            $display("Time=%0t WRITE blocked because FIFO is full", $time);
        end
    end

    always @(posedge rd_clk) begin
        if (r_inc && !rd_empty) begin
            $display("Time=%0t READ  data=%h full=%b empty=%b", $time, rd_data, wr_full, rd_empty);
        end else if (r_inc && rd_empty) begin
            $display("Time=%0t READ blocked because FIFO is empty", $time);
        end
    end

    initial begin
        // Initialize signals before pulsing the active-low resets.
        i = 0;
        seed = 1;
        wr_clk = 1'b0;
        rd_clk = 1'b0;
        wr_rst_n = 1'b1;
        rd_rst_n = 1'b1;
        w_inc = 1'b0;
        r_inc = 1'b0;
        wr_data = {DSIZE{1'b0}};

        #40;
        wr_rst_n = 1'b0;
        rd_rst_n = 1'b0;

        #40;
        wr_rst_n = 1'b1;
        rd_rst_n = 1'b1;

        // Write while read is enabled to show normal FIFO flow.
        $display("TEST CASE 1: Write data and read it back");
        r_inc = 1'b1;
        for (i = 0; i < 10; i = i + 1) begin
            wr_data = $random(seed) % 256;
            w_inc = 1'b1;
            #10;
            w_inc = 1'b0;
            #10;
        end

        // Continue writing past capacity and observe the full protection.
        $display("TEST CASE 2: Fill FIFO and try to write more");
        r_inc = 1'b0;
        w_inc = 1'b1;
        for (i = 0; i < DEPTH + 3; i = i + 1) begin
            wr_data = $random(seed) % 256;
            #10;
        end
        w_inc = 1'b0;

        // Read past the remaining contents and observe the empty protection.
        $display("TEST CASE 3: Empty FIFO and try to read more");
        r_inc = 1'b1;
        for (i = 0; i < DEPTH + 3; i = i + 1) begin
            #20;
        end
        r_inc = 1'b0;

        #40;
        $finish;
    end

//    initial begin
//        $dumpfile("dump.vcd");
//        $dumpvars(0, Async_FIFO_tb);
//    end

endmodule

Verilog/Async_FIFO.sim/sim_1/behav/xsim/dump.vcd
$date
   Thu Mar 26 15:39:35 2026
$end
$version
  2022.2
$end
$timescale
  1ps
$end
$scope module Async_FIFO_tb $end
$var reg 8 ! wr_data [7:0] $end
$var reg 1 " w_inc $end
$var reg 1 # r_inc $end
$var reg 1 $ wr_clk $end
$var reg 1 % rd_clk $end
$var reg 1 & wr_rst_n $end
$var reg 1 ' rd_rst_n $end
$var wire 8 ( rd_data [7:0] $end
$var wire 1 ) wr_full $end
$var wire 1 * rd_empty $end
$var integer 32 + i [31:0] $end
$var integer 32 , seed [31:0] $end
$scope module fifo $end
$var wire 1 - wr_clk $end
$var wire 1 . wr_rst_n $end
$var wire 1 / rd_clk $end
$var wire 1 0 rd_rst_n $end
$var wire 1 1 wr_en $end
$var wire 1 2 rd_en $end
$var wire 8 3 data_in [7:0] $end
$var wire 8 ( data_out [7:0] $end
$var wire 1 ) full $end
$var wire 1 * empty $end
$var wire 5 4 g_wptr_sync [4:0] $end
$var wire 5 5 g_rptr_sync [4:0] $end
$var wire 5 6 b_wptr [4:0] $end
$var wire 5 7 b_rptr [4:0] $end
$var wire 5 8 g_wptr [4:0] $end
$var wire 5 9 g_rptr [4:0] $end
$scope module sync_wptr_inst $end
$var reg 5 : data_out [4:0] $end
$var wire 5 8 data_in [4:0] $end
$var wire 1 / clk $end
$var wire 1 0 rst_n $end
$var reg 5 ; ff_1 [4:0] $end
$upscope $end
$scope module sync_rptr_inst $end
$var reg 5 < data_out [4:0] $end
$var wire 5 9 data_in [4:0] $end
$var wire 1 - clk $end
$var wire 1 . rst_n $end
$var reg 5 = ff_1 [4:0] $end
$upscope $end
$scope module wptr_full_inst $end
$var wire 1 - wr_clk $end
$var wire 1 . wr_rst_n $end
$var wire 1 1 wr_en $end
$var wire 5 5 g_rptr_sync [4:0] $end
$var reg 1 > full $end
$var reg 5 ? g_wptr [4:0] $end
$var reg 5 @ b_wptr [4:0] $end
$var wire 5 A b_wptr_next [4:0] $end
$var wire 5 B g_wptr_next [4:0] $end
$var wire 1 C wr_full $end
$upscope $end
$scope module rptr_empty_inst $end
$var wire 1 / rd_clk $end
$var wire 1 0 rd_rst_n $end
$var wire 1 2 rd_en $end
$var wire 5 4 g_wptr_sync [4:0] $end
$var reg 1 D empty $end
$var reg 5 E g_rptr [4:0] $end
$var reg 5 F b_rptr [4:0] $end
$var wire 5 G b_rptr_next [4:0] $end
$var wire 5 H g_rptr_next [4:0] $end
$var wire 1 I rd_empty $end
$upscope $end
$scope module fifo_mem_inst $end
$var wire 1 - wr_clk $end
$var wire 1 1 wr_en $end
$var wire 1 / rd_clk $end
$var wire 1 2 rd_en $end
$var wire 5 6 b_wptr [4:0] $end
$var wire 5 7 b_rptr [4:0] $end
$var wire 8 3 data_in [7:0] $end
$var wire 1 ) full $end
$var wire 1 * empty $end
$var wire 8 ( data_out [7:0] $end
$upscope $end
$upscope $end
$upscope $end
$enddefinitions $end
#0
$dumpvars
b0 !
0"
0#
0$
0%
1&
1'
bx (
x)
x*
b0 +
b1 ,
0-
1.
0/
10
01
02
b0 3
bx 4
bx 5
bx 6
bx 7
bx 8
bx 9
bx :
bx ;
bx <
bx =
x>
bx ?
bx @
bx A
bx B
xC
xD
bx E
bx F
bx G
bx H
xI
$end
#5000
1$
1-
#10000
0$
1%
0-
1/
#15000
1$
1-
#20000
0$
0%
0-
0/
#25000
1$
1-
#30000
0$
1%
0-
1/
#35000
1$
1-
#40000
0$
0%
0&
0'
0)
1*
0-
0.
0/
00
b0 4
b0 5
b0 6
b0 7
b0 8
b0 9
b0 :
b0 ;
b0 <
b0 =
0>
b0 ?
b0 @
b0 A
b0 B
0C
1D
b0 E
b0 F
b0 G
b0 H
1I
#45000
1$
1-
#50000
0$
1%
0-
1/
#55000
1$
1-
#60000
0$
0%
0-
0/
#65000
1$
1-
#70000
0$
1%
0-
1/
#75000
1$
1-
#80000
b0 !
1"
1#
0$
0%
1&
1'
0-
1.
0/
10
11
12
b1 A
b1 B
b0 G
#85000
1$
b0 (
1-
b1 6
b1 8
b1 ?
b1 @
b10 A
b11 B
#90000
0"
0$
1%
0-
1/
01
b1 ;
b1 A
b1 B
#95000
1$
1-
#100000
b111000 !
1"
0$
0%
b1 +
0-
0/
11
b111000 3
b10 A
b11 B
#105000
1$
1-
b10 6
b11 8
b11 ?
b10 @
b11 A
b10 B
#110000
0"
0$
1%
0-
1/
01
b1 4
b1 :
b11 ;
b10 A
b11 B
0I
#115000
1$
1-
#120000
b10000110 !
1"
0$
0%
b10 +
0-
0/
11
b10000110 3
b11 A
b10 B
#125000
1$
1-
b11 6
b10 8
b10 ?
b11 @
b100 A
b110 B
#130000
0"
0$
1%
0*
0-
1/
01
b11 4
b11 :
b10 ;
b11 A
b10 B
0D
b1 G
b1 H
0I
#135000
1$
1-
#140000
b1011100 !
1"
0$
0%
b11 +
0-
0/
11
b1011100 3
b100 A
b110 B
#145000
1$
1-
b100 6
b110 8
b110 ?
b100 @
b101 A
b111 B
#150000
0"
0$
1%
b111000 (
0-
1/
01
b10 4
b1 7
b1 9
b10 :
b110 ;
b100 A
b110 B
b1 E
b1 F
b10 G
b11 H
0I
#155000
1$
1-
b1 =
#160000
b11001110 !
1"
0$
0%
b100 +
0-
0/
11
b11001110 3
b101 A
b111 B
#165000
1$
1-
b1 5
b101 6
b111 8
b1 <
b111 ?
b101 @
b110 A
b101 B
#170000
0"
0$
1%
b10000110 (
0-
1/
01
b110 4
b10 7
b11 9
b110 :
b111 ;
b101 A
b111 B
b11 E
b10 F
b11 G
b10 H
0I
#175000
1$
1-
b11 =
#180000
b11000111 !
1"
0$
0%
b101 +
0-
0/
11
b11000111 3
b110 A
b101 B
#185000
1$
1-
b11 5
b110 6
b101 8
b11 <
b101 ?
b110 @
b111 A
b100 B
#190000
0"
0$
1%
b1011100 (
0-
1/
01
b111 4
b11 7
b10 9
b111 :
b101 ;
b110 A
b101 B
b10 E
b11 F
b100 G
b110 H
0I
#195000
1$
1-
b10 =
#200000
b11000110 !
1"
0$
0%
b110 +
0-
0/
11
b11000110 3
b111 A
b100 B
#205000
1$
1-
b10 5
b111 6
b100 8
b10 <
b100 ?
b111 @
b1000 A
b1100 B
#210000
0"
0$
1%
b11001110 (
0-
1/
01
b101 4
b100 7
b110 9
b101 :
b100 ;
b111 A
b100 B
b110 E
b100 F
b101 G
b111 H
0I
#215000
1$
1-
b110 =
#220000
b11110011 !
1"
0$
0%
b111 +
0-
0/
11
b11110011 3
b1000 A
b1100 B
#225000
1$
1-
b110 5
b1000 6
b1100 8
b110 <
b1100 ?
b1000 @
b1001 A
b1101 B
#230000
0"
0$
1%
b11000111 (
0-
1/
01
b100 4
b101 7
b111 9
b100 :
b1100 ;
b1000 A
b1100 B
b111 E
b101 F
b110 G
b101 H
0I
#235000
1$
1-
b111 =
#240000
b11000011 !
1"
0$
0%
b1000 +
0-
0/
11
b11000011 3
b1001 A
b1101 B
#245000
1$
1-
b111 5
b1001 6
b1101 8
b111 <
b1101 ?
b1001 @
b1010 A
b1111 B
#250000
0"
0$
1%
b11000110 (
0-
1/
01
b1100 4
b110 7
b101 9
b1100 :
b1101 ;
b1001 A
b1101 B
b101 E
b110 F
b111 G
b100 H
0I
#255000
1$
1-
b101 =
#260000
b1011111 !
1"
0$
0%
b1001 +
0-
0/
11
b1011111 3
b1010 A
b1111 B
#265000
1$
1-
b101 5
b1010 6
b1111 8
b101 <
b1111 ?
b1010 @
b1011 A
b1110 B
#270000
0"
0$
1%
b11110011 (
0-
1/
01
b1101 4
b111 7
b100 9
b1101 :
b1111 ;
b1010 A
b1111 B
b100 E
b111 F
b1000 G
b1100 H
0I
#275000
1$
1-
b100 =
#280000
b1000111 !
1"
0#
0$
0%
b0 +
0-
0/
11
02
b1000111 3
b1011 A
b1110 B
b111 G
b100 H
#285000
1$
1-
b100 5
b1011 6
b1110 8
b100 <
b1110 ?
b1011 @
b1100 A
b1010 B
#290000
b10001001 !
0$
1%
b1 +
0-
1/
b10001001 3
b1111 4
b1111 :
b1110 ;
#295000
1$
1-
b1100 6
b1010 8
b1010 ?
b1100 @
b1101 A
b1011 B
#300000
b1111110 !
0$
0%
b10 +
0-
0/
b1111110 3
#305000
1$
1-
b1101 6
b1011 8
b1011 ?
b1101 @
b1110 A
b1001 B
#310000
b1000101 !
0$
1%
b11 +
0-
1/
b1000101 3
b1110 4
b1110 :
b1011 ;
#315000
1$
1-
b1110 6
b1001 8
b1001 ?
b1110 @
b1111 A
b1000 B
#320000
b1011101 !
0$
0%
b100 +
0-
0/
b1011101 3
#325000
1$
1-
b1111 6
b1000 8
b1000 ?
b1111 @
b10000 A
b11000 B
#330000
b10010001 !
0$
1%
b101 +
0-
1/
b10010001 3
b1011 4
b1011 :
b1000 ;
#335000
1$
1-
b10000 6
b11000 8
b11000 ?
b10000 @
b10001 A
b11001 B
#340000
b1101110 !
0$
0%
b110 +
0-
0/
b1101110 3
#345000
1$
1-
b10001 6
b11001 8
b11001 ?
b10001 @
b10010 A
b11011 B
#350000
b10001111 !
0$
1%
b111 +
0-
1/
b10001111 3
b1000 4
b1000 :
b11001 ;
#355000
1$
1-
b10010 6
b11011 8
b11011 ?
b10010 @
b10011 A
b11010 B
#360000
b111100 !
0$
0%
b1000 +
0-
0/
b111100 3
#365000
1$
1-
b10011 6
b11010 8
b11010 ?
b10011 @
b10100 A
b11110 B
#370000
b11001001 !
0$
1%
b1001 +
0-
1/
b11001001 3
b11001 4
b11001 :
b11010 ;
#375000
1$
1-
b10100 6
b11110 8
b11110 ?
b10100 @
b10101 A
b11111 B
#380000
b11100011 !
0$
0%
b1010 +
0-
0/
b11100011 3
#385000
1$
1-
b10101 6
b11111 8
b11111 ?
b10101 @
b10110 A
b11101 B
#390000
b11011100 !
0$
1%
b1011 +
0-
1/
b11011100 3
b11010 4
b11010 :
b11111 ;
#395000
1$
1-
b10110 6
b11101 8
b11101 ?
b10110 @
b10111 A
b11100 B
1C
#400000
b101100 !
0$
0%
b1100 +
0-
0/
b101100 3
#405000
1$
1)
1-
b10111 6
b11100 8
1>
b11100 ?
b10111 @
b10111 A
#410000
b1011111 !
0$
1%
b1101 +
0-
1/
b1011111 3
b11111 4
b11111 :
b11100 ;
#415000
1$
1-
#420000
b10001 !
0$
0%
b1110 +
0-
0/
b10001 3
#425000
1$
1-
#430000
b11010001 !
0$
1%
b1111 +
0-
1/
b11010001 3
b11100 4
b11100 :
#435000
1$
1-
#440000
b0 !
0$
0%
b10000 +
0-
0/
b0 3
#445000
1$
1-
#450000
b11010001 !
0$
1%
b10001 +
0-
1/
b11010001 3
#455000
1$
1-
#460000
b11111111 !
0$
0%
b10010 +
0-
0/
b11111111 3
#465000
1$
1-
#470000
0"
1#
0$
1%
b11000011 (
b0 +
0-
1/
01
12
b1000 7
b10111 A
b1000 F
b1001 G
b1101 H
#475000
1$
1-
#480000
0$
0%
0-
0/
#485000
1$
1-
#490000
0$
1%
b1011111 (
b1 +
0-
1/
b1001 7
b1101 9
b1101 E
b1001 F
b1010 G
b1111 H
#495000
1$
1-
b1101 =
#500000
0$
0%
0-
0/
#505000
1$
1-
b1101 5
b1101 <
0C
#510000
0$
1%
b1000111 (
b10 +
0-
1/
b1010 7
b1111 9
b1111 E
b1010 F
b1011 G
b1110 H
#515000
1$
0)
1-
b1111 =
0>
b10111 A
#520000
0$
0%
0-
0/
#525000
1$
1-
b1111 5
b1111 <
#530000
0$
1%
b10001001 (
b11 +
0-
1/
b1011 7
b1110 9
b1110 E
b1011 F
b1100 G
b1010 H
#535000
1$
1-
b1110 =
#540000
0$
0%
0-
0/
#545000
1$
1-
b1110 5
b1110 <
#550000
0$
1%
b1111110 (
b100 +
0-
1/
b1100 7
b1010 9
b1010 E
b1100 F
b1101 G
b1011 H
#555000
1$
1-
b1010 =
#560000
0$
0%
0-
0/
#565000
1$
1-
b1010 5
b1010 <
#570000
0$
1%
b1000101 (
b101 +
0-
1/
b1101 7
b1011 9
b1011 E
b1101 F
b1110 G
b1001 H
#575000
1$
1-
b1011 =
#580000
0$
0%
0-
0/
#585000
1$
1-
b1011 5
b1011 <
#590000
0$
1%
b1011101 (
b110 +
0-
1/
b1110 7
b1001 9
b1001 E
b1110 F
b1111 G
b1000 H
#595000
1$
1-
b1001 =
#600000
0$
0%
0-
0/
#605000
1$
1-
b1001 5
b1001 <
#610000
0$
1%
b10010001 (
b111 +
0-
1/
b1111 7
b1000 9
b1000 E
b1111 F
b10000 G
b11000 H
#615000
1$
1-
b1000 =
#620000
0$
0%
0-
0/
#625000
1$
1-
b1000 5
b1000 <
#630000
0$
1%
b1101110 (
b1000 +
0-
1/
b10000 7
b11000 9
b11000 E
b10000 F
b10001 G
b11001 H
#635000
1$
1-
b11000 =
#640000
0$
0%
0-
0/
#645000
1$
1-
b11000 5
b11000 <
#650000
0$
1%
b10001111 (
b1001 +
0-
1/
b10001 7
b11001 9
b11001 E
b10001 F
b10010 G
b11011 H
#655000
1$
1-
b11001 =
#660000
0$
0%
0-
0/
#665000
1$
1-
b11001 5
b11001 <
#670000
0$
1%
b111100 (
b1010 +
0-
1/
b10010 7
b11011 9
b11011 E
b10010 F
b10011 G
b11010 H
#675000
1$
1-
b11011 =
#680000
0$
0%
0-
0/
#685000
1$
1-
b11011 5
b11011 <
#690000
0$
1%
b11001001 (
b1011 +
0-
1/
b10011 7
b11010 9
b11010 E
b10011 F
b10100 G
b11110 H
#695000
1$
1-
b11010 =
#700000
0$
0%
0-
0/
#705000
1$
1-
b11010 5
b11010 <
#710000
0$
1%
b11100011 (
b1100 +
0-
1/
b10100 7
b11110 9
b11110 E
b10100 F
b10101 G
b11111 H
#715000
1$
1-
b11110 =
#720000
0$
0%
0-
0/
#725000
1$
1-
b11110 5
b11110 <
#730000
0$
1%
b11011100 (
b1101 +
0-
1/
b10101 7
b11111 9
b11111 E
b10101 F
b10110 G
b11101 H
#735000
1$
1-
b11111 =
#740000
0$
0%
0-
0/
#745000
1$
1-
b11111 5
b11111 <
#750000
0$
1%
b101100 (
b1110 +
0-
1/
b10110 7
b11101 9
b11101 E
b10110 F
b10111 G
b11100 H
1I
#755000
1$
1-
b11101 =
#760000
0$
0%
0-
0/
#765000
1$
1-
b11101 5
b11101 <
#770000
0$
1%
b11110011 (
1*
b1111 +
0-
1/
b10111 7
b11100 9
1D
b11100 E
b10111 F
b10111 G
#775000
1$
1-
b11100 =
#780000
0$
0%
0-
0/
#785000
1$
1-
b11100 5
b11100 <
#790000
0$
1%
b10000 +
0-
1/
#795000
1$
1-
#800000
0$
0%
0-
0/
#805000
1$
1-
#810000
0$
1%
b10001 +
0-
1/
#815000
1$
1-
#820000
0$
0%
0-
0/
#825000
1$
1-
#830000
0$
1%
b10010 +
0-
1/
#835000
1$
1-
#840000
0$
0%
0-
0/
#845000
1$
1-
#850000
0#
0$
1%
b10011 +
0-
1/
02
b10111 G
